mihoyo_api/__init__.py
mihoyo_api/bbs.py
mihoyo_api/geetest.py
mihoyo_api/genshin.py
mihoyo_api/test.py
mihoyo_api/tool.py
mihoyo_api-1.1.dist-info/METADATA
mihoyo_api-1.1.dist-info/WHEEL
mihoyo_api-1.1.dist-info/top_level.txt
mihoyo_api-1.1.dist-info/RECORD
